pytest_codecov/__init__.py
pytest_codecov/codecov.py
pytest_codecov/git.py
pytest_codecov-0.7.0.dist-info/licenses/LICENSE
pytest_codecov-0.7.0.dist-info/METADATA
pytest_codecov-0.7.0.dist-info/WHEEL
pytest_codecov-0.7.0.dist-info/entry_points.txt
pytest_codecov-0.7.0.dist-info/top_level.txt
pytest_codecov-0.7.0.dist-info/RECORD
