Metadata-Version: 2.4
Name: pytest-codecov
Version: 0.7.0
Summary: Pytest plugin for uploading pytest-cov results to codecov.io
Author-email: David Salvisberg <david.salvisberg@seantis.ch>
Maintainer-email: David Salvisberg <david.salvisberg@seantis.ch>
License: 
Project-URL: Repository, https://github.com/seantis/pytest-codecov
Classifier: Framework :: Pytest
Classifier: Development Status :: 4 - Beta
Classifier: Intended Audience :: Developers
Classifier: Topic :: Software Development :: Testing
Classifier: Operating System :: OS Independent
Classifier: Programming Language :: Python
Classifier: Programming Language :: Python :: 3.8
Classifier: Programming Language :: Python :: 3.9
Classifier: Programming Language :: Python :: 3.10
Classifier: Programming Language :: Python :: 3.11
Classifier: Programming Language :: Python :: 3.12
Classifier: Programming Language :: Python :: 3.13
Classifier: Programming Language :: Python :: 3 :: Only
Classifier: Programming Language :: Python :: Implementation :: CPython
Classifier: Programming Language :: Python :: Implementation :: PyPy
Classifier: License :: OSI Approved :: MIT License
Requires-Python: >=3.8
License-File: LICENSE
Requires-Dist: pytest>=4.6.0
Requires-Dist: pytest-cov>=2.11.0
Requires-Dist: coverage[toml]>=5.2.1
Requires-Dist: requests>=2.25.1
Provides-Extra: git
Requires-Dist: GitPython>=3.1.15; extra == "git"
Dynamic: license-file
